fireblocks_defi_sdk_py/__init__.py
fireblocks_defi_sdk_py/chain.py
fireblocks_defi_sdk_py/web3_bridge.py
fireblocks_defi_sdk_py/tokenization/__init__.py
fireblocks_defi_sdk_py/tokenization/examples/custom_token_example.py
fireblocks_defi_sdk_py/tokenization/examples/erc20_example.py
fireblocks_defi_sdk_py/tokenization/examples/multi_token_example.py
fireblocks_defi_sdk_py/tokenization/examples/nft_example.py
fireblocks_defi_sdk_py/tokenization/tokens/__init__.py
fireblocks_defi_sdk_py/tokenization/tokens/base_token.py
fireblocks_defi_sdk_py/tokenization/tokens/custom_token.py
fireblocks_defi_sdk_py/tokenization/tokens/erc1155.py
fireblocks_defi_sdk_py/tokenization/tokens/erc721.py
fireblocks_defi_sdk_py/tokenization/utils/helpers.py
fireblocks_defi_sdk-1.1.0.dist-info/LICENSE
fireblocks_defi_sdk-1.1.0.dist-info/METADATA
fireblocks_defi_sdk-1.1.0.dist-info/WHEEL
fireblocks_defi_sdk-1.1.0.dist-info/top_level.txt
fireblocks_defi_sdk-1.1.0.dist-info/RECORD
