Metadata-Version: 2.1
Name: fireblocks-defi-sdk
Version: 1.1.0
Summary: fireblocks_defi_sdk_py
Home-page: https://github.com/fireblocks/fireblocks-defi-sdk-py
Download-URL: https://github.com/fireblocks/fireblocks-defi-sdk-py/archive/refs/tags/1.1.0.tar.gz
Author: Fireblocks
Author-email: fireblocks@fireblocks.com
License: MIT
Keywords: FIREBLOCKS,DeFi,SDK,PYTHON
Classifier: Development Status :: 3 - Alpha
Classifier: Intended Audience :: Developers
Classifier: Topic :: Software Development :: Build Tools
Classifier: License :: OSI Approved :: MIT License
Classifier: Programming Language :: Python :: 3.6
Classifier: Programming Language :: Python :: 3.7
Classifier: Programming Language :: Python :: 3.8
Classifier: Programming Language :: Python :: 3.9
Classifier: Programming Language :: Python :: 3.10
Classifier: Programming Language :: Python :: 3.11
License-File: LICENSE
Requires-Dist: fireblocks-sdk (==1.19.0)
Requires-Dist: web3 (==6.2.0)
